{"chunk_definitions":[{"row":37,"row_count":1,"visible":true,"expansion_state":0,"options":{"engine":"r","label":"unnamed-chunk-2"},"document_id":"398D1D9F","chunk_id":"c5464hq5f5hby","chunk_label":"unnamed-chunk-1"},{"row":41,"row_count":1,"visible":true,"expansion_state":0,"options":{"engine":"r","label":"unnamed-chunk-3"},"document_id":"398D1D9F","chunk_id":"c8b9t01xhblgj","chunk_label":"unnamed-chunk-2"},{"row":45,"row_count":1,"visible":true,"expansion_state":0,"options":{"engine":"r","label":"unnamed-chunk-4"},"document_id":"398D1D9F","chunk_id":"c2vmqtx3vbwtm","chunk_label":"unnamed-chunk-3"},{"row":49,"row_count":1,"visible":true,"expansion_state":0,"options":{"engine":"r","label":"unnamed-chunk-5"},"document_id":"398D1D9F","chunk_id":"cpf0pctnctfgs","chunk_label":"unnamed-chunk-4"},{"row":58,"row_count":1,"visible":true,"expansion_state":0,"options":{"engine":"r","label":"unnamed-chunk-6"},"document_id":"398D1D9F","chunk_id":"c266mj8s3j4sn","chunk_label":"unnamed-chunk-5"},{"row":76,"row_count":1,"visible":true,"expansion_state":0,"options":{"engine":"r","label":"unnamed-chunk-2"},"document_id":"398D1D9F","chunk_id":"crg1bdse2kueg","chunk_label":"unnamed-chunk-6"},{"row":87,"row_count":1,"visible":true,"expansion_state":0,"options":{"engine":"r","label":"unnamed-chunk-3"},"document_id":"398D1D9F","chunk_id":"c7ibvqh5vy2js","chunk_label":"unnamed-chunk-7"}],"doc_write_time":1659861183,"chunk_rendered_width":655}